README.md
setup.py
youtube_auto_comment_liker/__init__.py
youtube_auto_comment_liker.egg-info/PKG-INFO
youtube_auto_comment_liker.egg-info/SOURCES.txt
youtube_auto_comment_liker.egg-info/dependency_links.txt
youtube_auto_comment_liker.egg-info/requires.txt
youtube_auto_comment_liker.egg-info/top_level.txt